watson/__init__.py
watson/__main__.py
watson/core/__init__.py
watson/core/watson.py
watson/ressources/apikeys.json
watson/ressources/browsers.json
watson/ressources/sites.json
watson/userConfig/user_sites.json
watson/utils/__init__.py
watson/utils/miniBuster.py
watson_osint-0.1.8.dist-info/licenses/LICENSE
watson_osint-0.1.8.dist-info/METADATA
watson_osint-0.1.8.dist-info/WHEEL
watson_osint-0.1.8.dist-info/entry_points.txt
watson_osint-0.1.8.dist-info/top_level.txt
watson_osint-0.1.8.dist-info/RECORD
