Metadata-Version: 2.4
Name: watson-osint
Version: 0.1.8
Summary: Watson - Powerful username search engine
Home-page: https://github.com/margoul1/watson
Author: margoul1
Author-email: margoul1 <github.pydoctor@gmail.com>
License: MIT License
Project-URL: Homepage, https://github.com/margoul1/watson
Project-URL: Bug Tracker, https://github.com/margoul1/watson/issues
Keywords: osint,username,search,social media,investigation
Classifier: Programming Language :: Python :: 3
Classifier: License :: OSI Approved :: MIT License
Classifier: Operating System :: OS Independent
Classifier: Topic :: Security
Classifier: Topic :: Internet :: WWW/HTTP :: Indexing/Search
Requires-Python: >=3.6
License-File: LICENSE
Requires-Dist: requests
Requires-Dist: colorama
Requires-Dist: beautifulsoup4
Requires-Dist: fake_useragent
Requires-Dist: dnspython
Requires-Dist: google-api-python-client
Requires-Dist: cloudscraper
Requires-Dist: urllib3
Dynamic: author
Dynamic: home-page
Dynamic: license-file
Dynamic: requires-python
